{
	"cmake" : 
	{
		"generator" : 
		{
			"multiConfig" : false,
			"name" : "MinGW Makefiles"
		},
		"paths" : 
		{
			"cmake" : "D:/IDE/CLion 2022.3.2/bin/cmake/win/x64/bin/cmake.exe",
			"cpack" : "D:/IDE/CLion 2022.3.2/bin/cmake/win/x64/bin/cpack.exe",
			"ctest" : "D:/IDE/CLion 2022.3.2/bin/cmake/win/x64/bin/ctest.exe",
			"root" : "D:/IDE/CLion 2022.3.2/bin/cmake/win/x64/share/cmake-3.24"
		},
		"version" : 
		{
			"isDirty" : false,
			"major" : 3,
			"minor" : 24,
			"patch" : 2,
			"string" : "3.24.2",
			"suffix" : ""
		}
	},
	"objects" : 
	[
		{
			"jsonFile" : "codemodel-v2-b5ad1f6bc25469d23a2f.json",
			"kind" : "codemodel",
			"version" : 
			{
				"major" : 2,
				"minor" : 4
			}
		},
		{
			"jsonFile" : "cache-v2-d829bebda49773741fa1.json",
			"kind" : "cache",
			"version" : 
			{
				"major" : 2,
				"minor" : 0
			}
		},
		{
			"jsonFile" : "cmakeFiles-v1-9c8a8313b871051597cc.json",
			"kind" : "cmakeFiles",
			"version" : 
			{
				"major" : 1,
				"minor" : 0
			}
		},
		{
			"jsonFile" : "toolchains-v1-1dae79f0f28aa62519d3.json",
			"kind" : "toolchains",
			"version" : 
			{
				"major" : 1,
				"minor" : 0
			}
		}
	],
	"reply" : 
	{
		"cache-v2" : 
		{
			"jsonFile" : "cache-v2-d829bebda49773741fa1.json",
			"kind" : "cache",
			"version" : 
			{
				"major" : 2,
				"minor" : 0
			}
		},
		"cmakeFiles-v1" : 
		{
			"jsonFile" : "cmakeFiles-v1-9c8a8313b871051597cc.json",
			"kind" : "cmakeFiles",
			"version" : 
			{
				"major" : 1,
				"minor" : 0
			}
		},
		"codemodel-v2" : 
		{
			"jsonFile" : "codemodel-v2-b5ad1f6bc25469d23a2f.json",
			"kind" : "codemodel",
			"version" : 
			{
				"major" : 2,
				"minor" : 4
			}
		},
		"toolchains-v1" : 
		{
			"jsonFile" : "toolchains-v1-1dae79f0f28aa62519d3.json",
			"kind" : "toolchains",
			"version" : 
			{
				"major" : 1,
				"minor" : 0
			}
		}
	}
}
